pyrobo/__init__.py
pyrobo/cli.py
pyrobo/pyrobo.py
pyrobo-0.4.0.dist-info/AUTHORS.rst
pyrobo-0.4.0.dist-info/LICENSE
pyrobo-0.4.0.dist-info/METADATA
pyrobo-0.4.0.dist-info/WHEEL
pyrobo-0.4.0.dist-info/entry_points.txt
pyrobo-0.4.0.dist-info/top_level.txt
pyrobo-0.4.0.dist-info/RECORD
