Metadata-Version: 2.1
Name: pyrobo
Version: 0.4.0
Summary: Pyrobo contiene frases de la película colombiana La vendedora de rosas, basada en el cuento La vendedora de cerillas.
Home-page: https://github.com/nicoguaro/pyrobo
Author: Nicolás Guarín-Zapata
Author-email: nicoguarin@gmail.com
License: MIT license
Keywords: pyrobo
Platform: UNKNOWN
Classifier: Development Status :: 4 - Beta
Classifier: Intended Audience :: Developers
Classifier: License :: OSI Approved :: MIT License
Classifier: Natural Language :: Spanish
Classifier: Programming Language :: Python :: 3
Classifier: Programming Language :: Python :: 3.6
Classifier: Programming Language :: Python :: 3.7
Requires-Dist: Click (>=6.0)
Requires-Dist: numpy
